mdx_lightbox.py
markdown_lightbox-2.0.1.dist-info/LICENSE
markdown_lightbox-2.0.1.dist-info/METADATA
markdown_lightbox-2.0.1.dist-info/WHEEL
markdown_lightbox-2.0.1.dist-info/top_level.txt
markdown_lightbox-2.0.1.dist-info/RECORD
