Metadata-Version: 2.1
Name: markdown-lightbox
Version: 2.0.1
Summary: Markdown extension which turns images into lightbox
Home-page: https://github.com/kdm9/markdown-lightbox
Author: K.D.Murray, originally Alicia Schep
Author-email: foss@kdmurray.id.au
Classifier: Topic :: Text Processing :: Markup :: HTML
License-File: LICENSE
Requires-Dist: markdown >=3.0
